pyscap/__init__.py
pyscap/arf/__init__.py
pyscap/arf/ai_1_1.py
pyscap/arf/arf_1_1.py
pyscap/arf/reporting_core_1_1.py
pyscap/arf/x_al.py
pyscap/arf/x_nl.py
pyscap/common/__init__.py
pyscap/common/catalog.py
pyscap/common/namespaces.py
pyscap/common/simpledc20021212.py
pyscap/common/utils.py
pyscap/common/xlink.py
pyscap/common/xmldsig.py
pyscap/cpe/__init__.py
pyscap/cpe/cpe_1_0.py
pyscap/cpe/dictionary_2_3.py
pyscap/cpe/language_2_0.py
pyscap/cpe/language_2_3.py
pyscap/cpe/naming_2_3.py
pyscap/ocil/__init__.py
pyscap/ocil/ocil_2_0.py
pyscap/oval/__init__.py
pyscap/oval/common.py
pyscap/oval/definitions.py
pyscap/oval/directives.py
pyscap/oval/results.py
pyscap/oval/system_characteristics.py
pyscap/oval/variables.py
pyscap/sds/__init__.py
pyscap/sds/sds_1_3.py
pyscap/xccdf/__init__.py
pyscap/xccdf/platform_0_2_3.py
pyscap/xccdf/xccdf_1_1.py
pyscap/xccdf/xccdf_1_2.py
pyscap/xccdf/xccdfp_1_1.py
pyscap-0.1.3.dist-info/LICENSE
pyscap-0.1.3.dist-info/METADATA
pyscap-0.1.3.dist-info/WHEEL
pyscap-0.1.3.dist-info/top_level.txt
pyscap-0.1.3.dist-info/RECORD
