Metadata-Version: 2.1
Name: pyscap
Version: 0.1.3
Summary: Python package for handling Security Content Automation Protocol.
Home-page: https://github.com/Little-Tetra/pyscap
Author: Kevin Ju
License: MIT
Platform: UNKNOWN
Requires-Dist: xsdata
